{ "oldColors": [ { "rgb": 3881269.0, "g": 57.0, "r": 53.0, "collision": -1.0, "b": 59.0, "<unknown built-in variable>": 1.0 }, { "rgb": 15070455.0, "g": 244.0, "r": 247.0, "collision": -1.0, "b": 229.0, "<unknown built-in variable>": 1.0 }, { "rgb": 3571711.0, "g": 127.0, "r": 255.0, "collision": -1.0, "b": 54.0, "<unknown built-in variable>": 1.0 }, { "rgb": 6781051.0, "g": 120.0, "r": 123.0, "collision": -1.0, "b": 103.0, "<unknown built-in variable>": 1.0 } ], "colors": [ { "rgb": 5975808.0, "g": 47.0, "r": 0.0, "collision": -1.0, "b": 91.0, "<unknown built-in variable>": 1.0 }, { "rgb": 14805744.0, "g": 234.0, "r": 240.0, "collision": -1.0, "b": 225.0, "<unknown built-in variable>": 1.0 }, { "rgb": 6881238.0, "g": 255.0, "r": 214.0, "collision": -1.0, "b": 104.0, "<unknown built-in variable>": 1.0 }, { "rgb": 10664390.0, "g": 185.0, "r": 198.0, "collision": -1.0, "b": 162.0, "<unknown built-in variable>": 1.0 } ] }